htb_operator.py
command/__init__.py
command/api_key.py
command/badge.py
command/base.py
command/certificate.py
command/challenge.py
command/info.py
command/init.py
command/machine.py
command/prolabs.py
command/proxy.py
command/pwnbox.py
command/respect.py
command/season.py
command/sherlock.py
command/version.py
command/vhostcommand.py
command/vpn.py
console/__init__.py
console/argument_creator.py
console/cli_panel.py
console/cli_table.py
htb_operator-1.3.0.dist-info/licenses/LICENSE
htbapi/__init__.py
htbapi/activity.py
htbapi/badge.py
htbapi/base_user_profile.py
htbapi/certificate.py
htbapi/challenge.py
htbapi/client.py
htbapi/endgame.py
htbapi/fortress.py
htbapi/htb_http_request.py
htbapi/machine.py
htbapi/prolab.py
htbapi/pwnbox.py
htbapi/season.py
htbapi/sherlock.py
htbapi/user.py
htbapi/vpn.py
htbapi/exception/__init__.py
htbapi/exception/errors.py
htb_operator-1.3.0.dist-info/METADATA
htb_operator-1.3.0.dist-info/WHEEL
htb_operator-1.3.0.dist-info/entry_points.txt
htb_operator-1.3.0.dist-info/top_level.txt
htb_operator-1.3.0.dist-info/RECORD
