Metadata-Version: 2.4
Name: htb-operator
Version: 1.3.0
Summary: HTB-Operator - A CLI for accessing Hackthebox
Home-page: https://github.com/user0x1337/htb-operator
Author: user0x1337
Author-email: user0x1337 <user0x1337@protonmail.com>
License: GPLv3.0
Requires-Python: >=3.12
License-File: LICENSE
Requires-Dist: requests
Requires-Dist: colorama
Requires-Dist: pyjwt
Requires-Dist: tabulate
Requires-Dist: psutil
Requires-Dist: pexpect
Requires-Dist: pyreadline3
Requires-Dist: python-dateutil
Requires-Dist: libarchive-c
Requires-Dist: rich
Requires-Dist: pillow
Requires-Dist: python-hosts
Requires-Dist: psutil
Requires-Dist: beautifulsoup4
Requires-Dist: tqdm
Requires-Dist: paramiko
Requires-Dist: packaging
Requires-Dist: toml
Dynamic: author
Dynamic: home-page
Dynamic: license-file
